e.pdfminer.six-0.0.1.data/scripts/dumppdf.py
e.pdfminer.six-0.0.1.data/scripts/latin2ascii.py
e.pdfminer.six-0.0.1.data/scripts/pdf2txt.py
e.pdfminer.six-0.0.1.dist-info/DESCRIPTION.rst
e.pdfminer.six-0.0.1.dist-info/METADATA
e.pdfminer.six-0.0.1.dist-info/RECORD
e.pdfminer.six-0.0.1.dist-info/WHEEL
e.pdfminer.six-0.0.1.dist-info/metadata.json
e.pdfminer.six-0.0.1.dist-info/top_level.txt
pdfminer/__init__.py
pdfminer/arcfour.py
pdfminer/ascii85.py
pdfminer/ccitt.py
pdfminer/cmapdb.py
pdfminer/converter.py
pdfminer/encodingdb.py
pdfminer/fontmetrics.py
pdfminer/glyphlist.py
pdfminer/high_level.py
pdfminer/image.py
pdfminer/jbig2.py
pdfminer/latin_enc.py
pdfminer/layout.py
pdfminer/lzw.py
pdfminer/pdfcolor.py
pdfminer/pdfdevice.py
pdfminer/pdfdocument.py
pdfminer/pdffont.py
pdfminer/pdfinterp.py
pdfminer/pdfpage.py
pdfminer/pdfparser.py
pdfminer/pdftypes.py
pdfminer/psparser.py
pdfminer/rijndael.py
pdfminer/runlength.py
pdfminer/settings.py
pdfminer/utils.py
pdfminer/cmap/78-EUC-H.pickle.gz
pdfminer/cmap/78-EUC-V.pickle.gz
pdfminer/cmap/78-H.pickle.gz
pdfminer/cmap/78-RKSJ-H.pickle.gz
pdfminer/cmap/78-RKSJ-V.pickle.gz
pdfminer/cmap/78-V.pickle.gz
pdfminer/cmap/78ms-RKSJ-H.pickle.gz
pdfminer/cmap/78ms-RKSJ-V.pickle.gz
pdfminer/cmap/83pv-RKSJ-H.pickle.gz
pdfminer/cmap/83pv-RKSJ-V.pickle.gz
pdfminer/cmap/90ms-RKSJ-H.pickle.gz
pdfminer/cmap/90ms-RKSJ-V.pickle.gz
pdfminer/cmap/90msp-RKSJ-H.pickle.gz
pdfminer/cmap/90msp-RKSJ-V.pickle.gz
pdfminer/cmap/90pv-RKSJ-H.pickle.gz
pdfminer/cmap/90pv-RKSJ-V.pickle.gz
pdfminer/cmap/Add-H.pickle.gz
pdfminer/cmap/Add-RKSJ-H.pickle.gz
pdfminer/cmap/Add-RKSJ-V.pickle.gz
pdfminer/cmap/Add-V.pickle.gz
pdfminer/cmap/B5-H.pickle.gz
pdfminer/cmap/B5-V.pickle.gz
pdfminer/cmap/B5pc-H.pickle.gz
pdfminer/cmap/B5pc-V.pickle.gz
pdfminer/cmap/CNS-EUC-H.pickle.gz
pdfminer/cmap/CNS-EUC-V.pickle.gz
pdfminer/cmap/CNS1-H.pickle.gz
pdfminer/cmap/CNS1-V.pickle.gz
pdfminer/cmap/CNS2-H.pickle.gz
pdfminer/cmap/CNS2-V.pickle.gz
pdfminer/cmap/ETHK-B5-H.pickle.gz
pdfminer/cmap/ETHK-B5-V.pickle.gz
pdfminer/cmap/ETen-B5-H.pickle.gz
pdfminer/cmap/ETen-B5-V.pickle.gz
pdfminer/cmap/ETenms-B5-H.pickle.gz
pdfminer/cmap/ETenms-B5-V.pickle.gz
