Metadata-Version: 2.0
Name: e.pdfminer.six
Version: 0.0.1
Summary: PDF parser and analyzer
Home-page: https://github.com/pdfminer/pdfminer.six
Author: Yusuke Shinyama + Philippe Guglielmetti
Author-email: pdfminer@goulu.net
License: MIT/X
Keywords: pdf parser,pdf converter,layout analysis,text mining
Platform: UNKNOWN
Classifier: Programming Language :: Python
Classifier: Programming Language :: Python :: 2.6
Classifier: Programming Language :: Python :: 2.7
Classifier: Programming Language :: Python :: 3.4
Classifier: Programming Language :: Python :: 3.5
Classifier: Programming Language :: Python :: 3.6
Classifier: Development Status :: 5 - Production/Stable
Classifier: Environment :: Console
Classifier: Intended Audience :: Developers
Classifier: Intended Audience :: Science/Research
Classifier: License :: OSI Approved :: MIT License
Classifier: Topic :: Text Processing
Requires-Dist: pycryptodome
Requires-Dist: six
Requires-Dist: sortedcontainers
Requires-Dist: chardet; python_version > "3.0"
Provides-Extra: dev
Requires-Dist: nose; extra == 'dev'
Requires-Dist: tox; extra == 'dev'
Provides-Extra: docs
Requires-Dist: sphinx; extra == 'docs'
Requires-Dist: sphinx-argparse; extra == 'docs'
